mercatus/__init__.py
mercatus/datasets.py
mercatus-0.0.1.dist-info/METADATA
mercatus-0.0.1.dist-info/WHEEL
mercatus-0.0.1.dist-info/top_level.txt
mercatus-0.0.1.dist-info/RECORD
