Metadata-Version: 2.1
Name: mercatus
Version: 0.0.1
Summary: AI implementor for exchange markets
Home-page: https://github.com/gialdetti/mercatus
Author: Eyal Gal
Author-email: eyalgl@gmail.com
License: UNKNOWN
Platform: UNKNOWN
Classifier: Programming Language :: Python :: 3.9
Requires-Dist: numpy
Requires-Dist: pandas
